{
  "id": "6",
  "title": "세련된 주방 리모델링",
  "category": "주거공간",
  "imageUrl": "/images/project/project-sleek-kitchen.jpg",
  "description": "내구한 공간을 세련되고 기능적인 요리 공간으로 변화시킨 포괄적인 주방 리모델링입니다. 이 디자인은 미니멀리스트 스타일의 참장, 통합된 가전제품, 열정적인 요리사를 위한 흐름이 좋은 작업 공간을 특징으로 합니다.",
  "client": "나카무라 가족",
  "date": "2023-07-18",
  "tags": ["모던", "주거공간", "주방", "미니멀리스트"],
  "servicesProvided": ["주방 디자인", "소재 선정", "가전제품 통합", "조명 디자인"],
  "images": [
    { "src": "/images/project/project-sleek-kitchen.jpg", "alt": "아일랜드가 있는 모던 주방" },
    { "src": "/images/project/project-sleek-kitchen-detail2.jpg", "alt": "맞춤형 참장과 통합된 가전제품" }
  ],
  "testimonial": {
    "quote": "주방이 이제 우리 집의 중심이 되었어요. 아름답고 기능적이며, 요리하는 일이 즐거움이 되었습니다!",
    "author": "히로시 & 케이코 N."
  }
}
